django_posts_api/__init__.py
django_posts_api/apps.py
django_posts_api/posts/__init__.py
django_posts_api/posts/__main__.py
django_posts_api/posts/admin.py
django_posts_api/posts/apps.py
django_posts_api/posts/models.py
django_posts_api/posts/tests.py
django_posts_api/posts/views.py
django_posts_api/posts/api/__init__.py
django_posts_api/posts/api/urls.py
django_posts_api/posts/api/views.py
django_posts_api/posts/migrations/0001_initial.py
django_posts_api/posts/migrations/0002_post_titlee.py
django_posts_api/posts/migrations/0003_post_titleee.py
django_posts_api/posts/migrations/0004_post_titleeee.py
django_posts_api/posts/migrations/__init__.py
django_posts_api-0.0.15.dist-info/LICENSE
django_posts_api-0.0.15.dist-info/METADATA
django_posts_api-0.0.15.dist-info/WHEEL
django_posts_api-0.0.15.dist-info/entry_points.txt
django_posts_api-0.0.15.dist-info/top_level.txt
django_posts_api-0.0.15.dist-info/RECORD
