Metadata-Version: 2.1
Name: django-posts-api
Version: 0.0.15
Summary: A small example plugin package
Author-email: Fadi Ghattas <fadoghattas100@outlook.com>
License: MIT License        
Project-URL: repository, https://github.com/fadighattas100/django_posts_api
Project-URL: documentation, https://github.com/fadighattas100/django_posts_api
Keywords: posts-api,tutorial
Classifier: License :: OSI Approved :: MIT License
Classifier: Programming Language :: Python
Classifier: Programming Language :: Python :: 3
Requires-Python: >=3.8
License-File: LICENSE
Requires-Dist: html2text
Requires-Dist: tomli ; python_version < "3.11"
Provides-Extra: build
Requires-Dist: build ; extra == 'build'
Requires-Dist: twine ; extra == 'build'
Provides-Extra: dev
Requires-Dist: black ; extra == 'dev'
Requires-Dist: bumpver ; extra == 'dev'
Requires-Dist: isort ; extra == 'dev'
Requires-Dist: mypy ; extra == 'dev'
Requires-Dist: pytest ; extra == 'dev'
